{"id":495397883,"parent_id":495397883,"created_at":"2025-06-14T01:03:01.120873Z","updated_at":"2025-11-18T19:44:47.903756Z","checked_at":"2025-11-18T19:44:47.903756Z","changed_at":"2025-10-04T03:22:53.956907Z","experience_change_last_identified_at":"2025-06-14T01:03:01.120873Z","is_deleted":0,"is_parent":1,"public_profile_id":839062991,"linkedin_url":"https://www.linkedin.com/in/nachiket11","linkedin_shorthand_names":["nachiket-jawalikar-a3b0001b5","nachiket11"],"historical_ids":[495397883],"full_name":"Nachiket Jawalikar","first_name":"Nachiket","first_name_initial":"N","middle_name":null,"middle_name_initial":null,"last_name":"Jawalikar","last_name_initial":"J","headline":"Working Student as Junior Program Manager| MS in Management | Technical University of Munich (TUM)","summary":"Self-driven in managing cross-functional teams for successful project execution…","picture_url":"https://media.licdn.com/dms/image/v2/D4E03AQEUVpL9lLrtjw/profile-displayphoto-shrink_200_200/profile-displayphoto-shrink_200_200/0/1728408290430?e=2147483647&v=beta&t=irtuCSUF_ex5S54i0EcpccTgZprgxCACBHDl8o4Q_Fg","location_country":"Germany","location_country_iso2":"DE","location_country_iso3":"DEU","location_full":"Munich, Bavaria, Germany","location_regions":["Europe","Western Europe","EMEA","EU"],"location_city":"Munich","location_state":"Bavaria","interests":[],"inferred_skills":["management","planning","analysis","aviation","engineering","technology","sales","projects","digital","marketing","inform","negotiations","efficiency","less","training","project execution","project management","strategic planning","data analysis","management skills","business development","digital marketing","product development","human resources"],"historical_skills":[],"connections_count":500,"followers_count":736,"services":null,"primary_professional_email":null,"primary_professional_email_status":null,"professional_emails_collection":[],"is_working":1,"active_experience_company_id":31065968,"active_experience_title":"Working Student As Junior Program Manager","active_experience_description":null,"active_experience_department":null,"active_experience_management_level":null,"is_decision_maker":null,"total_experience_duration_months":19,"total_experience_duration_months_breakdown_department":[{"department":"Sales","total_experience_duration_months":4},{"department":"Education","total_experience_duration_months":7},{"department":"Other","total_experience_duration_months":15},{"department":"Project Management","total_experience_duration_months":6},{"department":"Human Resources","total_experience_duration_months":1}],"total_experience_duration_months_breakdown_management_level":[{"management_level":"Manager","total_experience_duration_months":6},{"management_level":"Other","total_experience_duration_months":15},{"management_level":"Intern","total_experience_duration_months":12}],"experience":[{"active_experience":1,"position_title":"Working Student As Junior Program Manager","department":null,"management_level":null,"location":null,"description":null,"date_from":"September 2024","date_from_year":2024,"date_from_month":9,"date_to":null,"date_to_year":null,"date_to_month":null,"duration_months":14,"company_id":31065968,"company_name":"Deutsche Aircraft","company_type":"Privately Held","company_founded_year":2020,"company_followers_count":45640,"company_website":"https://www.bit.ly/3x9fhxx","company_facebook_url":["https://www.facebook.com/deu.aircraft"],"company_twitter_url":["https://www.twitter.com/deu_aircraft"],"company_linkedin_url":"https://www.linkedin.com/company/deutsche-aircraft","company_size_range":"501-1000 employees","company_employees_count":387,"company_industry":"Aviation & Aerospace","company_categories_and_keywords":["aviation","operational flexibility","carbon neutral flights","german manufacturer","technological innovation","regional commercial aircraft","aerospace","air transportation","clean energy","greentech","innovation management","manufacturing","technical support","training"],"company_annual_revenue_source_5":429884000,"company_annual_revenue_currency_source_5":"USD","company_annual_revenue_source_1":null,"company_annual_revenue_currency_source_1":null,"company_employees_count_change_yearly_percentage":25.24271844660194,"company_last_funding_round_date":null,"company_last_funding_round_amount_raised":null,"company_hq_full_address":"Junkersstraße 2; Wessling, Bavaria 82234, DE","company_hq_country":"Germany","company_hq_regions":["Europe","Western Europe","EMEA","EU"],"company_hq_country_iso2":"DE","company_hq_country_iso3":"DEU","company_hq_city":null,"company_hq_state":null,"company_hq_street":null,"company_hq_zipcode":null,"company_last_updated_at":"2025-11-08","company_stock_ticker":[],"company_is_b2b":1,"order_in_profile":1},{"active_experience":0,"position_title":"Project Study","department":"Project Management","management_level":"Manager","location":"Munich, Bavaria, Germany","description":null,"date_from":"October 2024","date_from_year":2024,"date_from_month":10,"date_to":"April 2025","date_to_year":2025,"date_to_month":4,"duration_months":6,"company_id":8924179,"company_name":"Allianz","company_type":"Public Company","company_founded_year":null,"company_followers_count":1165350,"company_website":"https://www.allianz.com","company_facebook_url":["https://www.facebook.com/allianz","https://www.facebook.com/allianzcareers"],"company_twitter_url":["https://www.twitter.com/allianz"],"company_linkedin_url":"https://www.linkedin.com/company/allianz","company_size_range":"10,001+ employees","company_employees_count":117001,"company_industry":"Financial Services","company_categories_and_keywords":["insurance","asset management","financials","global","allianz","career opportunities","worldwide","financial-services","financial-management","life-insurance","financial services","intellectual property"],"company_annual_revenue_source_5":103544581700,"company_annual_revenue_currency_source_5":"USD","company_annual_revenue_source_1":null,"company_annual_revenue_currency_source_1":null,"company_employees_count_change_yearly_percentage":-2.03868159640563,"company_last_funding_round_date":"2018-04-16","company_last_funding_round_amount_raised":null,"company_hq_full_address":"Koeniginstrasse 28; Munich, 80802, DE","company_hq_country":"Germany","company_hq_regions":["Europe","Western Europe","EMEA","EU"],"company_hq_country_iso2":"DE","company_hq_country_iso3":"DEU","company_hq_city":null,"company_hq_state":null,"company_hq_street":null,"company_hq_zipcode":null,"company_last_updated_at":"2025-11-03","company_stock_ticker":[{"exchange":null,"ticker":"ALV.DE"},{"exchange":"FRA","ticker":"ALV"}],"company_is_b2b":0,"order_in_profile":2},{"active_experience":0,"position_title":"Human Resources Intern","department":"Human Resources","management_level":"Intern","location":null,"description":"Optimized recruitment processes by posting job openings, screening resumes, scheduling interviews, and verifying references to ensure prompt onboarding of new hires. Coordinated new hire orientation preparation, scheduling, and administration. Led the recruiting department during internship, demonstrating strong leadership and the ability to delegate tasks effectively, expediting the overall recruiting process.","date_from":"January 2023","date_from_year":2023,"date_from_month":1,"date_to":"February 2023","date_to_year":2023,"date_to_month":2,"duration_months":1,"company_id":null,"company_name":"Bavch Edutech","company_type":null,"company_founded_year":null,"company_followers_count":null,"company_website":null,"company_facebook_url":[],"company_twitter_url":[],"company_linkedin_url":null,"company_size_range":null,"company_employees_count":null,"company_industry":null,"company_categories_and_keywords":[],"company_annual_revenue_source_5":null,"company_annual_revenue_currency_source_5":null,"company_annual_revenue_source_1":null,"company_annual_revenue_currency_source_1":null,"company_employees_count_change_yearly_percentage":null,"company_last_funding_round_date":null,"company_last_funding_round_amount_raised":null,"company_hq_full_address":null,"company_hq_country":null,"company_hq_regions":[],"company_hq_country_iso2":null,"company_hq_country_iso3":null,"company_hq_city":null,"company_hq_state":null,"company_hq_street":null,"company_hq_zipcode":null,"company_last_updated_at":null,"company_stock_ticker":[],"company_is_b2b":null,"order_in_profile":3},{"active_experience":0,"position_title":"Business Development Intern","department":"Sales","management_level":"Intern","location":null,"description":"Successfully increased the app's user base by 22% and converted 150 leads into clients within a month. I collaborated on sales proposals and business plans, managed multiple projects, and led a digital marketing campaign that boosted brand visibility and qualified leads. I analyzed data to inform market strategies and facilitated strategic partner negotiations, securing favorable terms. I implemented process improvements that increased team efficiency by 15% and led a customer feedback initiative, influencing product development and service enhancements. Show less","date_from":"August 2022","date_from_year":2022,"date_from_month":8,"date_to":"December 2022","date_to_year":2022,"date_to_month":12,"duration_months":4,"company_id":null,"company_name":"The Bigger Story","company_type":null,"company_founded_year":null,"company_followers_count":null,"company_website":null,"company_facebook_url":[],"company_twitter_url":[],"company_linkedin_url":null,"company_size_range":null,"company_employees_count":null,"company_industry":null,"company_categories_and_keywords":[],"company_annual_revenue_source_5":null,"company_annual_revenue_currency_source_5":null,"company_annual_revenue_source_1":null,"company_annual_revenue_currency_source_1":null,"company_employees_count_change_yearly_percentage":null,"company_last_funding_round_date":null,"company_last_funding_round_amount_raised":null,"company_hq_full_address":null,"company_hq_country":null,"company_hq_regions":[],"company_hq_country_iso2":null,"company_hq_country_iso3":null,"company_hq_city":null,"company_hq_state":null,"company_hq_street":null,"company_hq_zipcode":null,"company_last_updated_at":null,"company_stock_ticker":[],"company_is_b2b":null,"order_in_profile":4},{"active_experience":0,"position_title":"On Job Training","department":"Education","management_level":"Intern","location":"Hyderabad, Telangana, India","description":"As an aircraft maintenance trainee, I gained hands-on experience in inspections, repairs, and maintenance. I improved efficiency by streamlining inventory management and optimizing workflows. Additionally, I effectively communicated between maintenance teams, management, and other departments.","date_from":"January 2022","date_from_year":2022,"date_from_month":1,"date_to":"August 2022","date_to_year":2022,"date_to_month":8,"duration_months":7,"company_id":12320560,"company_name":"AIR-INDIA ENGINEERING SERVICES LIMITED","company_type":null,"company_founded_year":null,"company_followers_count":3169,"company_website":null,"company_facebook_url":[],"company_twitter_url":[],"company_linkedin_url":"https://www.linkedin.com/company/air-india-engineering-services-limited","company_size_range":null,"company_employees_count":596,"company_industry":null,"company_categories_and_keywords":[],"company_annual_revenue_source_5":null,"company_annual_revenue_currency_source_5":null,"company_annual_revenue_source_1":null,"company_annual_revenue_currency_source_1":null,"company_employees_count_change_yearly_percentage":-3.403565640194489,"company_last_funding_round_date":null,"company_last_funding_round_amount_raised":null,"company_hq_full_address":"AIRLINES HOUSE 113 GURUDWARA RAKABGANJ ROAD NEW; DELHI, Delhi 110001, IN","company_hq_country":"India","company_hq_regions":["Asia","Southern Asia","APAC"],"company_hq_country_iso2":"IN","company_hq_country_iso3":"IND","company_hq_city":null,"company_hq_state":null,"company_hq_street":null,"company_hq_zipcode":null,"company_last_updated_at":"2025-10-14","company_stock_ticker":[],"company_is_b2b":null,"order_in_profile":5}],"projected_base_salary_p25":null,"projected_base_salary_median":null,"projected_base_salary_p75":null,"projected_base_salary_period":null,"projected_base_salary_currency":null,"projected_base_salary_updated_at":null,"projected_additional_salary":[],"projected_additional_salary_period":null,"projected_additional_salary_currency":null,"projected_additional_salary_updated_at":null,"projected_total_salary_p25":null,"projected_total_salary_median":null,"projected_total_salary_p75":null,"projected_total_salary_period":null,"projected_total_salary_currency":null,"projected_total_salary_updated_at":null,"last_graduation_date":2025,"education_degrees":["Master in Management","Higher Secondary Education, 95.4 %","M.Sc in aviation ground stream, Aeronautics/Aviation/Aerospace Science and Technology, General, First class with Distinction"],"education":[{"degree":"Master in Management","description":null,"institution_url":"https://www.linkedin.com/school/technische-universitat-munchen","institution_name":"Technical University of Munich","institution_full_address":"Arcisstraße 21, München; Munich, Bavaria 80333, DE","institution_country_iso2":"DE","institution_country_iso3":"DEU","institution_regions":["Europe","Western Europe","EMEA","EU"],"institution_city":null,"institution_state":null,"institution_street":null,"institution_zipcode":null,"date_from_year":2023,"date_to_year":2025,"activities_and_societies":null,"order_in_profile":1},{"degree":"M.Sc in aviation ground stream, Aeronautics/Aviation/Aerospace Science and Technology, General, First class with Distinction","description":null,"institution_url":"https://www.linkedin.com/school/jawaharlal-nehru-technological-university","institution_name":"Jawaharlal Nehru Technological University","institution_full_address":"Kukatpally Hyderabad 500 072 Andhra Pradesh; Kukatpalli, Hyderabad 500070, IN","institution_country_iso2":"IN","institution_country_iso3":"IND","institution_regions":["Asia","Southern Asia","APAC"],"institution_city":null,"institution_state":null,"institution_street":null,"institution_zipcode":null,"date_from_year":2018,"date_to_year":2023,"activities_and_societies":null,"order_in_profile":2},{"degree":"Higher Secondary Education, 95.4 %","description":null,"institution_url":"https://www.linkedin.com/school/narayana-junior-college---india","institution_name":"Narayana Junior College - India","institution_full_address":null,"institution_country_iso2":null,"institution_country_iso3":null,"institution_regions":[],"institution_city":null,"institution_state":null,"institution_street":null,"institution_zipcode":null,"date_from_year":2016,"date_to_year":2018,"activities_and_societies":null,"order_in_profile":3}],"recommendations_count":null,"recommendations":[],"activity":[{"activity_url":"https://www.linkedin.com/posts/ipek-ece-nurhan-057447257_im-happy-to-share-that-im-starting-a-new-activity-7394413203432210432-10ag","title":"I’m happy to share that I’m starting a new position as Process Mining Working Student at KPMG!","action":"Liked by","order_in_profile":1},{"activity_url":"https://www.linkedin.com/posts/harishragula_newbeginnings-aviationmaintenance-aircraftengines-activity-7393172997936799744-dEtv","title":"\"New Chapter, New Beginnings\" ✈️\n\nAs I move forward to explore exciting new opportunities, I’m taking a moment to reflect on my incredible journey…","action":"Liked by","order_in_profile":2},{"activity_url":"https://www.linkedin.com/posts/laurentin-harter_happy-to-share-that-ive-just-started-my-activity-7386366275158999040-zJni","title":"Happy to share that I’ve just started my next internship at KPMG in the Performance & Strategy team!\n\nI’m looking forward to gaining first-hand…","action":"Liked by","order_in_profile":3},{"activity_url":"https://www.linkedin.com/posts/lilian-aracely-aybar-bb85b0150_s-sheleads-allianz-activity-7384994642104176640-pf1C","title":"What an inspiring week! 💫\nLast week, Allianz hosted the #s.heleads 2025 Forum in Munich, bringing together almost 140 participants from different…","action":"Liked by","order_in_profile":4},{"activity_url":"https://www.linkedin.com/posts/danielhemhauser_stop-calling-yourself-a-project-manager-activity-7391807235829501952-wEST","title":"Stop Calling Yourself a Project Manager\n\nHold on... It's not what you think.\n\nThe title \"Project Manager\" has become too small for what the job…","action":"Liked by","order_in_profile":5},{"activity_url":"https://www.linkedin.com/posts/deutsche-aircraft_teamda-toulousemarathon-tmre26-activity-7391413914283991040-r3kw","title":"🥇🏃 Huge congrats to our amazing #TeamDA for taking on the #ToulouseMarathon last weekend! Their unstoppable spirit mirrors our drive for excellence…","action":"Liked by","order_in_profile":6},{"activity_url":"https://www.linkedin.com/posts/suyashbadiger_dear-connections-i-am-very-happy-to-share-activity-7381569119344594944-0GDO","title":"Dear Connections,\n\nI am very happy to share with you all that I have joined BASF as a full-time graduate trainee in BASF European Business Services…","action":"Liked by","order_in_profile":7},{"activity_url":"https://www.linkedin.com/posts/gayatri-borawake_i-was-contemplating-at-first-whether-i-activity-7378039052098314240-TUBI","title":"🌱 I was contemplating at first whether I should post this or not. As LinkedIn is slowly becoming more or less like other social media, we should…","action":"Liked by","order_in_profile":8},{"activity_url":"https://www.linkedin.com/posts/siddhesh-chavan-2409_fem-turbomachinery-vibrations-activity-7377424402205892608-Xpwf","title":"✅ Concluded the FEM in Turbomachinery Practical Course\nThis course was a hands-on experience analyzing and simulating the 5th stage rotor of a…","action":"Liked by","order_in_profile":9},{"activity_url":"https://www.linkedin.com/posts/siddhesh-chavan-2409_fea-hypermesh-optistruct-activity-7372369254995726337-ctxw","title":"I recently completed a project using Altair HyperMesh and OptiStruct to analyze a stiffened aluminium wing panel under realistic loading conditions…","action":"Liked by","order_in_profile":10}],"awards":[],"courses":[],"certifications":[],"languages":[],"patents_count":null,"patents_topics":[],"patents":[],"publications_count":null,"publications_topics":[],"publications":[],"projects_count":2,"projects_topics":["Winner, Sport-Tech Hackathon","Thesis on Evolution of Aircraft Wings"],"projects":[{"name":"Winner, Sport-Tech Hackathon","description":"Led team in developing innovative basketball halftime show using ASB Lumiflex LED sports floor, enhancing fan engagement, entertainment, sponsor integration, and sports relevance.","project_url":null,"date_from":null,"date_from_year":null,"date_from_month":null,"date_to":null,"date_to_year":null,"date_to_month":null,"order_in_profile":1},{"name":"Thesis on Evolution of Aircraft Wings","description":"Researched wing shape evolution, using case studies and performance data to understand design influences. Integrated materials science with aerodynamic efficiency to develop innovative wing compositions.","project_url":null,"date_from":"Oct 2021","date_from_year":2021,"date_from_month":10,"date_to":"Apr 2022","date_to_year":2022,"date_to_month":4,"order_in_profile":2}],"organizations":[],"github_url":"https://github.com/Nachiket11","github_username":"Nachiket11","github_mapping_confidence":50,"github_contributions_count":5,"github_repos_summary":[{"name":"join-us","summary":"An introductory repo for people to join DSC PCCoE Community.","stars":0,"contributions_count":0},{"name":"Inventory-Management-System","summary":null,"stars":0,"contributions_count":1},{"name":"cv","summary":null,"stars":0,"contributions_count":2},{"name":"TSF","summary":null,"stars":0,"contributions_count":1}],"profile_root_field_changes_summary":[{"field_name":"deleted","change_type":"updated","last_changed_at":"2025-06-14 01:03:01.120873"},{"field_name":"shorthand_name","change_type":"updated","last_changed_at":"2025-08-18 14:22:05.167957"},{"field_name":"follower_count","change_type":"updated","last_changed_at":"2025-10-04 03:22:53.956907"},{"field_name":"experience_count","change_type":"updated","last_changed_at":"2025-06-14 01:03:01.120873"},{"field_name":"profile_photo_url","change_type":"new","last_changed_at":"2025-06-14 01:03:01.120873"},{"field_name":"connections_count","change_type":"updated","last_changed_at":"2025-06-14 01:03:01.120873"},{"field_name":"profile_url","change_type":"updated","last_changed_at":"2025-08-18 14:22:05.167957"},{"field_name":"headline","change_type":"updated","last_changed_at":"2025-06-14 01:03:01.120873"},{"field_name":"summary","change_type":"new","last_changed_at":"2025-06-14 01:03:01.120873"}],"profile_collection_field_changes_summary":[{"field_name":"education","last_changed_at":"2025-10-04 03:22:53.956907"},{"field_name":"experience","last_changed_at":"2025-07-30 03:49:44.829756"},{"field_name":"projects","last_changed_at":"2025-06-14 01:03:01.120873"},{"field_name":"volunteering_positions","last_changed_at":"2025-06-14 01:03:01.120873"},{"field_name":"activity","last_changed_at":"2025-10-04 03:22:53.956907"}],"experience_recently_started":[],"experience_recently_closed":[]}